{"66000":["19","018","García",2,[["Centro Villa de Garcia (casco)",0],["Los Aljibes",1]]],"66003":["19","018","García",0,[["Hacienda del Sol",0],["Héroes de Capellanía",1],["Los Nogales",1],["Mirador de Garcia",0],["Paseo de las Minas",0],["Praderas de Lincoln",1],["Privadas de las Villas",0],["Privadas de Lincoln",1],["Rincón del Fraile",1],["Villas del Alcali",1]]],"66004":["19","018","García",2,[["Las Arboledas",0],["Las Villas",0],["Paseo de las Torres",0],["Paseo Del Nogal",0],["Privalia García",1],["Real de Capellanía",1],["Sierra Real",0],["Urbi Villa del Prado",1],["Valle de San Jose",0],["Valle de San José 2do Sector",1],["Villas de los Nogales",0]]],"66005":["19","018","García",2,[["Benito Juárez",0],["Cedral",0],["El Fraile II",0],["Emiliano Zapata",0],["Fomorrey Sobrevilla",0],["Fraile I",0],["Infonavit los Nogales",0],["Las Palmas",0],["Morelos",0],["Nuevo Amanecer",0],["Real de San Martin",0],["Real de Villas de Garcia",0],["San Jose",0],["San Martin",0],["Torres de Garcia",0],["Villas de San Martin",0]]],"66006":["19","018","García",2,[["Alfonzo Martinez Dominguez",0],["Balcones de García",1],["Colinas Del Rio",0],["División del Norte",0],["Fomorrey Nogales I",24],["Las Bugambilias",1],["Martin Gonzalez",0],["Misión del Norte",0],["Nogales II",24],["Valles del Mirador",0]]],"66007":["19","018","García",2,[["Avance Popular",0],["Paseo de Capellanía",1],["Riberas de Capellania",0]]],"66008":["19","018","García",2,[["La Cruz",0],["Los Arcángeles",1],["Miguel Hidalgo",0],["Nuevo Renacimiento",0],["Popular Jose Páez Garcia",0],["Real de Minas",1],["Valle San Felipe",0]]],"66009":["19","018","García",0,[["Los Encinos Residencial",1],["San Juan Bautista",0]]],"66010":["19","018","NULL",1,[["Rinconada",20]]],"66012":["19","018","NULL",0,[["Joya del Carrizal",1],["Residencial Santa Elena",1],["Residencial Santa Lucía",1],["Residencial Santa Mónica",1],["Villazul",1]]],"66013":["19","018","NULL",0,[["Paseo de Lincoln",1]]],"66017":["19","018","NULL",1,[["Libramiento Arco Vial",18],["Parque Industrial POLITEK",18]]],"66020":["19","018","NULL",1,[["Emiliano Zapata",7],["La Soledad Estación",14]]],"66022":["19","018","NULL",1,[["La Gruta",1]]],"66023":["19","018","NULL",0,[["Arco Vial",18],["Ciudad Industrial Mitras",0],["Lomas de Garcia",0],["Los Parques Residencial",0],["Misión San Juan",1],["Mitras Bicentenario Sector Reforma",1],["Mitras Poniente",1],["Mitras Poniente Bicentenario",1],["Paraje San José",1],["Parques Diamante",1],["Rancho Mitras",0],["Valle de las Grutas",1],["Valle de Lincoln San Agustín",1],["Valle de Lincoln San José",1],["Villas Del Poniente",1]]],"66024":["19","018","NULL",0,[["Las Lomas",1]]],"66025":["19","018","NULL",1,[["Valle de San Blas",1]]],"66026":["19","018","NULL",1,[["Valle de Lincoln",1],["Valle de Lincoln Sector el Fraile",1],["Valle de Lincoln Sector Elite",1]]],"66027":["19","018","NULL",0,[["Santa Sofia",1]]],"66030":["19","018","NULL",1,[["Grutas de Villa de Garcia",7]]],"66033":["19","018","NULL",0,[["Las Brisas Residencial",1]]],"66035":["19","018","NULL",0,[["Cumbres Elite Premier",1],["Cumbres San Patricio",1],["Valle de Cumbres",1]]],"66036":["19","018","NULL",0,[["Ciudad Cumbres",1],["Cumbres Provenza",1]]],"66037":["19","018","NULL",0,[["Santa María",1]]],"66040":["19","018","NULL",1,[["La Cruz",7]]],"66042":["19","018","NULL",1,[["Icamole",13]]],"66050":["19","021","Ciudad General Escobedo",0,[["Del Valle",0],["Don Lalo",0],["Encinas las Piedra",0],["Gral. Escobedo Centro",0],["Jardines de Escobedo II",0],["Jardines Del Canada",0],["La Cuchilla",0],["Las Encinas",0],["Los Elizondo",0],["Los Eucaliptos",0],["Los Saldañas",0],["Miravista 3er Sector",0],["Miravista I",0],["Miravista II",0],["Privadas Diamante",1],["Residencial Encinas",0],["Residencial las Quintas",1],["Ricardo Flores Magón Infonavit I",3],["Ricardo Flores Magón Infonavit III",0],["Rincón de Miravista",1],["Rinconada Flores Magón Infonavit II",0],["Shalom",2],["Torres Diamante",2],["Villa Alta",1]]],"66051":["19","021","Ciudad General Escobedo",0,[["Jardines Escobedo I",0],["Plaza Sol",0]]],"66052":["19","021","Ciudad General Escobedo",0,[["Arboledas de Escobedo",0],["Balcones Del Norte 1er Sector",0],["Balcones Del Norte 2do Sector",0],["Desarrollo Industrial GP Tecnocentro",9],["Ébanos y Nueva Esperanza",0],["Emiliano Zapata",0],["Fernando Amilpa Predio",0],["Jardines de la Reyna",0],["Los Altos",0],["Los Olivos",1],["Niños Héroes",0],["Nueva Castilla",0],["Portal de la Hacienda",0],["Puerta de Anáhuac",0],["Rio Pesquería",0],["Rio Pesquería Norte",0],["Rio Pesquería Nuevas Puentes",0],["Rio Pesquería Poniente",0],["Sócrates Rizzo Unión Comerciantes",0],["Unión de Alfareros",0]]],"66053":["19","021","Ciudad General Escobedo",0,[["Agropecuaria",0],["Belisario Dominguez",0],["Chamizal",0],["Lázaro Cárdenas Agropecuaria Sur",0],["Los Arcos",0],["Los Girasoles II",0],["Los Nogales",0],["Privadas de San José",1],["Privadas del Los Sauces",1],["Raul Caballero",0],["Rincón de Las Encinas",1],["San Jose de los Sauces",0],["Valle de Escobedo",0]]],"66054":["19","021","Ciudad General Escobedo",0,[["Anáhuac Campoamor",0],["Anáhuac la Pergola",0],["Ex Hacienda el Canada",0],["Haciendas del Canada",0],["La Encomienda",1],["Puerta del Norte Fraccionamiento Residencial",0],["Rancho El 15",7]]],"66055":["19","021","Ciudad General Escobedo",0,[["California 2do Sector",0],["California Fraccionamiento Primer Sector",0],["Celestino Gasca",0],["Felipe Carrillo Puerto",0],["Felipe Carrillo Puerto II",0],["Felipe Carrillo Puerto III",0],["Felipe Carrillo Puerto IV",0],["Haciendas de Anáhuac I",0],["Haciendas de Anáhuac II",0],["Insurgentes Infonavit",0],["Jolla de Anáhuac Sector Nápoles",0],["Jolla de Anáhuac Sector Venecia",0],["Joyas de Anáhuac Sector Florencia",0],["Lázaro Cárdenas Ampliación",0],["Los Pinos",0],["Nexxus Residencial Sector Cristal",0],["Nexxus Residencial Sector Diamante",0],["Nexxus Residencial Sector Esmeralda",1],["Nexxus Residencial Sector Platino",1],["Nexxus Residencial Sector Rubí",1],["Nexxus Residencial Sector Zafiro",1],["Parque Industrial Nexxus XXI",9],["Portal de Escobedo",1],["Privada Del Angel",1],["Privadas Bougambilias",0],["Residencial Pinos",0],["Roble Nuevo",0],["Topo Grande IV",0],["Valle Nord",1],["Villas de Escobedo II",1],["Villas Del Parque",0]]],"66056":["19","021","Ciudad General Escobedo",0,[["Balcones de Anáhuac I",0],["Balcones de Anáhuac II",0],["Bosques Quebec",0],["El Topito",0],["Guadalupe Victoria",0],["Hilario Ayala Predio",0],["Lomas de Escobedo I",0],["Lomas de Escobedo II",0],["Los Girasoles I",0],["Monterreal I",0],["Monterreal II",0],["Monterreal III",0],["Monterreal IV",0],["Monterreal IX",0],["Monterreal V",0],["Monterreal VI",0],["Monterreal X",0],["Monterreal XI",0],["Monterreal XII",0],["Praderas de Girasoles",0],["Riberas de Girasoles 1 Sector",1],["Topo Grande",0],["Valle de Girasoles",0],["Villas de Escobedo",0]]],"66057":["19","021","Ciudad General Escobedo",0,[["Fuentes de Escobedo",1],["Hacienda Escobedo",1],["Los Rincones Residencial",1],["Monterreal Infonavit",0],["Novus Sendero",1],["Nuestra Señora de Fátima",0],["Privada Residencial Aviana",1],["Residencial Escobedo",1]]],"66058":["19","021","Ciudad General Escobedo",0,[["16 de Septiembre",0],["24 de Febrero",0],["Dirona Aduana Interior",0],["El Canadá",1],["Ex Hacienda Infonavit",0],["Jardines de Escobedo III",0],["La Loma",0],["Las Hadas",1],["Las Malvinas",0],["Lázaro Cárdenas",0],["Lázaro Cárdenas",24],["Los Girasoles III",0],["Martires 36",0],["Praderas de Topo Grande",0],["Solidaridad",0],["Ucam",0]]],"66059":["19","021","Ciudad General Escobedo",0,[["Calzadas Anáhuac",1],["Cerradas de Anáhuac",1],["Cerradas de Anáhuac Sector Contemporáneo",1],["Cerradas de Anáhuac Sector Premier",1],["El Centenario",0],["Hacienda los Cantu 1er Sector",1],["Hacienda los Cantu 2do Sector",1],["Himalaya",1],["Himalaya Sector Niza",1],["La Cantera",1],["La Cantera Privada Residencial",0],["Misión de Anáhuac 1er Sector",0],["Nexxus Residencial Sector Dorado",0],["Paraje Anáhuac",1],["Privadas de Anáhuac Sector  Mediterráneo",1],["Privadas de Anáhuac Sector Español",1],["Privadas de Anáhuac Sector Francés",1],["Privadas de Anáhuac Sector Inglés",1],["Privadas de Anáhuac Sector Irlandes",0],["Privadas de Lindora",0],["Privadas del Canada",1],["Quintas de Anáhuac",1],["Valle Del Canada",0],["Villas de Anáhuac",1],["Villas de Anáhuac Sector Alpes",1]]],"66061":["19","021","Ciudad General Escobedo",0,[["Fomerrey 52 Pedregal del Topo",0],["Jardines de San Martin",0],["Lomas de San Genaro",0],["Parque Industrial II",0],["Parque Industrial III",0],["Pedregal de Escobedo",1],["San Martin",0]]],"66062":["19","021","Ciudad General Escobedo",0,[["Gloria Mendiola",0],["La Isla",0],["Parque Industrial I",0],["Parque Industrial Periférico",9],["Paso Cucharas",0],["Villas de San Francisco",1]]],"66063":["19","021","Ciudad General Escobedo",0,[["19 de Julio",0],["5 de Mayo",0],["Balcones Del Rio",0],["Nueva Escobedo Ampliación",0],["San Isidro",0]]],"66064":["19","021","Ciudad General Escobedo",0,[["18 de Octubre",0],["Ciudad San Marcos Sector Pionero",1],["Fomerrey La Unidad",3],["Fomerrey Santa Martha",0],["La Concordia",23],["Las Flores",1],["Los Vergeles",1],["Nueva Esperanza Mzas 117 y 120",0],["Nuevo Escobedo",0],["Nuevo Escobedo",24],["Portal del Fraile 1er Sector",1],["Portal del Fraile 4ta Sector",1],["Privadas de Camino Real",0],["Riveras de los Naranjos",0],["Valle de San Francisco",1],["Vida",0],["Villas de San Martín 1er Etapa",0],["Villas de San Martín 2da Etapa",0]]],"66065":["19","021","Ciudad General Escobedo",0,[["Colinas del Topo Ampliación",24],["Eulalio Villarreal Ayala",0],["Eulalio Villarreal Ayala",24],["Fomerrey 49 \"Colinas del Topo\"",0],["Fomerrey Santa Lucia",0],["La Ilusión",0],["Serranías 1er Sector",1],["Serranías 2do Sector",1]]],"66067":["19","021","Ciudad General Escobedo",0,[["Alianza",1],["Alianza",0],["Arcos Del Sol",0],["El Rosario",0],["Los Angeles",0],["Los Nogales",0],["Naranjos",0],["Portal Valle de San Bernabe",0],["San Gabriel",0],["Villas de San Bernabe",0]]],"66068":["19","021","Ciudad General Escobedo",0,[["Los Alebrijes",1],["Pedregal de San Agustín",1]]],"66070":["19","021","Ciudad General Escobedo",0,[["Lomas de San Genaro 3er Sector",0],["Monte Horeb",0],["Provileon",0],["Puerta Del Sol",1],["Santaluz",0],["Villa de los Ayala",0]]],"66072":["19","021","Ciudad General Escobedo",0,[["5to. Centenario",0],["Bosques de Escobedo",0],["Brianzzas Residencial",1],["Cortijo los Ayala",1],["Hacienda Del Topo I",0],["Hacienda Del Topo II",0],["Hacienda los  Vergeles",1],["Hacienda los Ayala",0],["La Providencia",1],["Paseo Real",1],["Paso Cucharas II",0],["Progreso Paso Cucharas",0],["Renacimiento",1]]],"66073":["19","021","Ciudad General Escobedo",0,[["Adelitas de Villa",0],["Colinas de Anáhuac",0],["Fomerrey 9 Solidaridad",0],["Fomerrey Lomas de Aztlán",0],["Lomas I",1],["Lomas II",1],["Los Girasoles IV",0],["San Genaro 3er Sector",0],["San Genaro I",0],["San Genaro II",0],["Santa Julia",1]]],"66074":["19","021","Ciudad General Escobedo",0,[["Mira Sur",0],["Mira Sur 1",0]]],"66075":["19","021","Ciudad General Escobedo",0,[["Fomerrey 36 Raul Caballero",0]]],"66080":["19","021","Ciudad General Escobedo",0,[["Andres Caballero Moreno Agrop",0]]],"66083":["19","021","Ciudad General Escobedo",0,[["Zona Industrial",18]]],"66084":["19","021","Ciudad General Escobedo",0,[["Alianza Real",0],["Alianza Real Sector Oaxaca",0],["Alianza Real Sector Yucatán",0],["Arco Vial Fomerrey Agropecuaria",0],["Lázaro Cárdenas Agropecuaria del Norte",0],["Palmiras",1]]],"66085":["19","021","Ciudad General Escobedo",0,[["Ampliación Monclova",24],["Monclova",0],["Monclovita",0],["Portal de Piedra",0],["Praderas de San Francisco",1],["Praderas de San Francisco Sector 2",1],["San Miguel",0],["San Miguel de los Garza (La Luz)",0],["Valle de San Miguel",0]]],"66100":["19","048","Ciudad Santa Catarina",0,[["La Fama",0],["Privada Acueducto",0],["Privada Antigua",0],["Privada La Bolita",0]]],"66110":["19","048","Ciudad Santa Catarina",0,[["Cimas del Pte",0]]],"66114":["19","048","Ciudad Santa Catarina",0,[["Cerro de las Mitras",0],["Cima de las Mitras",0],["Raul Salinas",0],["Raul Salinas",24]]],"66115":["19","048","Ciudad Santa Catarina",0,[["Jardín de las Mitras",0],["La Fama 4",0]]],"66116":["19","048","Ciudad Santa Catarina",0,[["Fama II",0],["Fama IV",1],["Fama V",0]]],"66117":["19","048","Ciudad Santa Catarina",0,[["La Fama 1",0]]],"66118":["19","048","Ciudad Santa Catarina",0,[["Eugenio Canavati CTM",0],["Fama III",0]]],"66119":["19","048","Ciudad Santa Catarina",0,[["Arboledas de las Mitras",0],["Carlos Salinas de Gortari",0],["Lomas de La Fama",0],["Lomas Del Mirador",0]]],"66120":["19","048","Ciudad Santa Catarina",0,[["Balcones de San Humberto",0],["Los Portales",0],["Los Portales I",0],["Los Portales II",0],["San Humberto",0],["Villas de San Humberto",0],["Villas los Portales",0]]],"66129":["19","048","Ciudad Santa Catarina",0,[["Coop la Unión",0],["La Ermita",0],["Prados de San Jorge",0],["Prados de San Jose",0],["Privadas del Poniente",1],["Prov del Pte 3 Sec",0],["Provivienda del Pte 1 Sec",23],["Provivienda del Pte 2 Sec",23],["Unión",23]]],"66130":["19","048","Ciudad Santa Catarina",0,[["Indeco",0]]],"66139":["19","048","Ciudad Santa Catarina",0,[["Fomerrey 2",0],["Rincón de las Mitras",0]]],"66140":["19","048","Ciudad Santa Catarina",0,[["Jose Lopez Portillo",0]]],"66143":["19","048","Ciudad Santa Catarina",0,[["Industrial Monte de los Olivos",0]]],"66144":["19","048","Ciudad Santa Catarina",0,[["Residencial Cuauhtémoc",3]]],"66145":["19","048","Ciudad Santa Catarina",0,[["Hacienda los Portales",0]]],"66147":["19","048","Ciudad Santa Catarina",0,[["Santa Magdalena",0]]],"66149":["19","048","Ciudad Santa Catarina",0,[["Trabajadores",0]]],"66150":["19","048","Ciudad Santa Catarina",0,[["Los Treviño",0],["Parques la Fama",0],["Privada Treviño",0]]],"66159":["19","048","Ciudad Santa Catarina",0,[["Cooperativa Del Norte",0]]],"66160":["19","048","Ciudad Santa Catarina",0,[["Benito Juárez",0]]],"66165":["19","048","Ciudad Santa Catarina",0,[["Campania I",0],["Jardines de La Fama",0],["Privadas Ondara",1],["Valle de La Sierra",0]]],"66166":["19","048","Ciudad Santa Catarina",0,[["Campania",0]]],"66167":["19","048","Ciudad Santa Catarina",0,[["La Española",0]]],"66168":["19","048","Ciudad Santa Catarina",0,[["La Concordia",23]]],"66169":["19","048","Ciudad Santa Catarina",0,[["Efimex",0]]],"66170":["19","048","Ciudad Santa Catarina",0,[["Protexa",0]]],"66179":["19","048","Ciudad Santa Catarina",0,[["Montenegro",0]]],"66180":["19","048","Ciudad Santa Catarina",0,[["Jesús M Garza",0]]],"66187":["19","048","Ciudad Santa Catarina",0,[["Las Palmas",0]]],"66188":["19","048","Ciudad Santa Catarina",0,[["Cantizal",1],["La Fraternidad",0],["Residencial Olinca",1]]],"66189":["19","048","Ciudad Santa Catarina",0,[["La Barrica",0]]],"66190":["19","048","Ciudad Santa Catarina",0,[["Lomas de San Isidro",0],["San Isidro",0]]],"66195":["19","048","Ciudad Santa Catarina",0,[["Nueva Fortaleza",0]]],"66196":["19","048","Ciudad Santa Catarina",0,[["Hacienda La Banda",0],["La Banda",0],["Los Cenizos",1],["Miguel Hidalgo",0],["Residencial Cordillera",1],["Valle Poniente Sector Olinca",1],["Vía Cordillera",1]]],"66197":["19","048","Ciudad Santa Catarina",0,[["El Aguacatal",0],["Huasteca Real",0],["Las Montañas",0],["Loma Blanca",0]]],"66198":["19","048","Ciudad Santa Catarina",0,[["La Fortaleza",0]]],"66199":["19","048","Ciudad Santa Catarina",0,[["Idelfonso Vázquez",0]]],"66200":["19","019","San Pedro Garza García",0,[["San Pedro Garza Garcia Centro",0]]],"66210":["19","019","San Pedro Garza García",0,[["La Leona",0],["San Pedro 400",0],["San Pedro 400 Ampliación Norte",0],["Unidad Habitacional San Pedro",3]]],"66214":["19","019","San Pedro Garza García",0,[["El Obispo",0],["El Obispo 2",0],["Villa del Obispo",0]]],"66215":["19","019","San Pedro Garza García",0,[["San Pedro",3]]],"66216":["19","019","San Pedro Garza García",0,[["El Obispo",0],["Vista Montaña 1er Sector",0],["Vista Montaña 2 Sector",0],["Vista Montaña 3 Sector",0],["Zona Clouhtier",0]]],"66217":["19","019","San Pedro Garza García",0,[["Plan de Ayala",0],["Zona Industrial",18]]],"66218":["19","019","San Pedro Garza García",0,[["Echeverría",0],["Lucio Blanco 1er Sector",0],["Lucio Blanco 2do Sector",0],["Valle del Seminario 1 Sector",0],["Valle del Seminario 2 Sector",0]]],"66219":["19","019","San Pedro Garza García",0,[["Revolución 1er Sector",0],["Revolución 2do Sector",3],["Revolución 3er Sector",0],["Revolución 4to Sector",0],["Revolución 5to Sector",0],["Zona Revolución",0]]],"66220":["19","019","San Pedro Garza García",0,[["Del Valle",0],["Jardines Del Valle",0]]],"66224":["19","019","San Pedro Garza García",0,[["Fuentes del David",0],["Fuentes del Valle",0],["Fuentes del Valle Sector Colinas",0],["Residencial Santa Barbara la Cripta",22],["Zona Fuentes del Valle",0],["Zona los Sabinos",0],["Zona Santa Bárbara Poniente",0]]],"66225":["19","019","San Pedro Garza García",0,[["La Joya",0],["Zona del Valle",0]]],"66226":["19","019","San Pedro Garza García",0,[["Bugambilias",23],["Valle Del Mezquite",0]]],"66227":["19","019","San Pedro Garza García",0,[["Las Capillas",0],["Los Olivos",0],["San Francisco",0]]],"66228":["19","019","San Pedro Garza García",0,[["Residencial San Carlos",0],["Zona de Los Callejones",0]]],"66230":["19","019","San Pedro Garza García",0,[["Codornices Aldama",0],["Condominio",0],["Jardines Coloniales 1er Sector",0],["Jardines Coloniales 2 Sector",0],["Jardines Coloniales 3er Sector",0],["La Cima 1er Sector",0],["La Cúspide",0],["La Finca",0],["La Ventana",0],["Las Codornices",1],["Las Uvas",0],["Las Verandas",0],["Misión Del Valle",1],["Morelos",23],["Prados de La Sierra",0],["Privada Versalles",1],["Residencial Los Cubos",0],["Rincón Colonial",0],["San Gabriel",0],["San José",0],["San Pedro",0],["Villa Campanario",0],["Zona Hacienda San Francisco",0],["Zona la Cima",0],["Zona Palo Blanco",0],["Zona Rosario",0]]],"66233":["19","019","San Pedro Garza García",0,[["Las Sendas Andalucía",0],["Las Sendas Galicias",0],["Misión del Valle 3",1],["Santa Elena",0],["Zona Valle Poniente",0]]],"66234":["19","019","San Pedro Garza García",0,[["Villa Montaña Campestre",0]]],"66235":["19","019","San Pedro Garza García",0,[["La Cima 2do Sector",0],["La Cima 3er Sector",0],["Los Olmos",1],["Villa Montaña 1er Sector",0],["Villa Montaña 2 Sector",0]]],"66236":["19","019","San Pedro Garza García",0,[["Jardines de Mirasierra",0],["Palo Blanco",0],["Palo Blanco Sector El Edén",0],["Residencial Palo Blanco",0],["Villas de Santa Bárbara",0]]],"66237":["19","019","San Pedro Garza García",0,[["Los Sauces 1er Sector",0],["Los Sauces 2 Sector",0]]],"66238":["19","019","San Pedro Garza García",0,[["Jesús M Garza",0],["Lázaro Garza Ayala",0],["Lindavista",0],["Lucio Blanco 3er Sector",0],["Mirador de Vasconcelos",0],["Rincón de San Francisco",0],["Valle de Vasconcelos",0],["Zona los Sauces",0],["Zona Mirador Vazconcelos",0]]],"66239":["19","019","San Pedro Garza García",0,[["Hacienda de los Callejones",0],["Los Pinos 1er Sector",0],["Los Pinos 2 Sector (Asentamiento Irregular)",0],["Nemesio Garcia Naranjo",0],["Residencial las Amapas",1],["Rincón de Corregidora",0],["Volkswagen",0]]],"66240":["19","019","San Pedro Garza García",0,[["La Barranca",0],["La Cooperativa",0],["La Montaña",0],["Lomas de Tampiquito",0],["Mirasierra 1er Sector",0],["Mirasierra 2do Sector",0],["Mirasierra 3er Sector",0],["Mirasierra 4to Sector",0],["Mirasierra 5to Sector",0],["Olímpico",0],["Privada San Andrés",1],["Provivienda",0],["Rincón de La Montaña 1er Sector",0],["Rincón de la Montaña 2 Sector",0],["Rincón de la Montaña 3 Sector",0],["Tampiquito",0],["Zona La Ventana",0],["Zona Mirasierra",0],["Zona Valle del Mezquite",0]]],"66244":["19","019","San Pedro Garza García",0,[["Capistrano",0],["Lomas del Bosque",0],["Lomas Valle Sector Convento",0],["Los Fresnos",0],["Privada 20 de Noviembre",1]]],"66245":["19","019","San Pedro Garza García",0,[["Barranca Del Pedregal",0]]],"66246":["19","019","San Pedro Garza García",0,[["Hacienda Del Valle",0]]],"66247":["19","019","San Pedro Garza García",0,[["Hacienda El Rosario",0],["Hacienda las Campanas",0],["La Parvada",0],["Mansión Del Rosario",0],["Tampiquito",24]]],"66249":["19","019","San Pedro Garza García",0,[["Cerrada Moralillo",0],["Moralillo",0],["Villas de Terrasol",0]]],"66250":["19","019","San Pedro Garza García",0,[["Bosques del Valle 1er Sector",0],["Bosques del Valle 2do Sector",0],["Bosques del Valle 3er Sector",0],["Bosques del Valle 4to Sector",0],["Bosques del Valle 5to Sector",0],["Bosques del Valle Ampliación 5 Sector",0],["Fátima",0],["Jerónimo Siller",0],["Privada Río Ebro",1],["Privada Sierra Madre",0],["Valle de Chipinque",0],["Zona Jerónimo Siller",0],["Zona Privada Río Tamazunchale",0]]],"66254":["19","019","San Pedro Garza García",0,[["Carrizalejo",0]]],"66256":["19","019","San Pedro Garza García",0,[["Lomas Del Valle",0]]],"66257":["19","019","San Pedro Garza García",0,[["Del Valle Sector Fátima",0],["Zona Fátima",0]]],"66259":["19","019","San Pedro Garza García",0,[["Cortijo Del Valle",0],["Gómez Morin",5],["La Cañada",0],["Rincón de Carrizalejo",0],["Zona Antigua Exhacienda Carrizalejo",0],["Zona Carrizalejo",0],["Zona la Alianza",0]]],"66260":["19","019","San Pedro Garza García",0,[["Ampliación Canteras",0],["Ampliación Valle del Mirador",24],["Corporativo Proser",0],["Del Valle Oriente",0],["Hacienda de La Sierra",0],["Jardines de Campestre",0],["Portal de Santa Engracia",0],["Residencial Canteras",22],["Residencial San Agustin 1 Sector",0],["Residencial San Agustín 2 Sector",22],["San Mateo",22],["Zona San Agustín",0]]],"66263":["19","019","San Pedro Garza García",0,[["Zona Campestre",0],["Zona Santa Engracia",0]]],"66264":["19","019","San Pedro Garza García",0,[["Jardines del Campestre",0]]],"66265":["19","019","San Pedro Garza García",0,[["Valle Del Campestre",0],["Zona la Diana",0]]],"66266":["19","019","San Pedro Garza García",0,[["Cojunto Habitacional Renzo",23],["La Admiranza",0],["La Diana",1],["Los Arcángeles",22],["Mirador Del Campestre",1],["Residencial Frida Kahalo",22],["Residencial Santa Bárbara 1 Sector",0],["Residencial Santa Bárbara 2 Sector",0],["Verona",0],["Villas de San Agustin",0],["Vista Real",1],["Zona Loma Blanca Poniente",0],["Zona Loma Larga Oriente",0],["Zona Valle Oriente Norte",0]]],"66267":["19","019","San Pedro Garza García",0,[["Santa Engracia",0]]],"66268":["19","019","San Pedro Garza García",0,[["Del Valle Sect Norte",0],["Privada Santa Engracia",0],["Valle de Santa Engracia",0],["Villas de Santa Engracia",0],["Zona Valle Santa Engracia",0]]],"66269":["19","019","San Pedro Garza García",0,[["Del Valle Sect Oriente",0]]],"66270":["19","019","San Pedro Garza García",0,[["Colinas de San Agustin",0],["Los Colorines",1],["Misión San Patricio",0],["Residencial Galeana",22],["San Agustin Campestre",0],["San Patricio",1],["Veredalta",0],["Zona Lomas de San Agustín",0],["Zona Tampiquito",0]]],"66273":["19","019","San Pedro Garza García",0,[["Corporativo Santa Engracia 1 Sector",0],["Corporativo Santa Engracia 2 Sector",0],["Privada Gruta",1],["Villas de Aragón",0],["Zona Montebello",0]]],"66274":["19","019","San Pedro Garza García",0,[["Ampliación Jardines de San Agustín 3er Sector",0],["El Secreto",1],["Jardines de San Agustin",1],["Zona Antigua Exhacienda San Agustín",0]]],"66275":["19","019","San Pedro Garza García",0,[["Mesa de la Corona",0],["Vistas del Valle",0]]],"66276":["19","019","San Pedro Garza García",0,[["Hacienda San Agustin",0],["Villa las Palmas",1],["Zona Hacienda San Agustín",0],["Zona Lomas del Campestre",0]]],"66277":["19","019","San Pedro Garza García",0,[["La Encantada",0],["Las Ceibas",1],["Privada Real de San Agustín",1],["Privada San Roberto",0],["Santa Cruz",0],["Turquesa",1]]],"66278":["19","019","San Pedro Garza García",0,[["Alto Eucalipto",0],["Alto Jazmín",0],["Antigua Hacienda San Agustin",0],["Balcones de San Agustin",0],["Balcones Del Campestre",1],["Colonia Valle Oriente Sur",0],["Colonial San Agustin",1],["Corporativo Prodesa",0],["El Refugio",0],["Flor de Mayo",0],["La Muralla",0],["Las Calzadas",1],["Las Privanzas 3 Sector Segunda Etapa",0],["Las Privanzas Primero",0],["Las Privanzas Segundo",0],["Las Querenzas",1],["Lomas de San Agustín 1er Sector",0],["Lomas de San Agustín 2 Sector",0],["Lomas de San Agustín 3 Sector",0],["Lomas del Campestre",1],["Los Amates",0],["Los Quetzales",1],["Los Rincones",0],["Misión de San Agustín",0],["Parque Corporativo Uccaly",0],["Privada Lomas de San Agustin",0],["Privanza Alicante",1],["Privanza Fundadores",0],["Privanza Toledo",1],["Privanza Venecia",1],["Privanzas",1],["Privanzas 4 Sector 1 Etapa",1],["Privanzas Alejandría",1],["Privanzas Burdeos",1],["Privanzas Córcega",1],["Privanzas Marsella",1],["Privanzas Martinica",1],["Privanzas Mónaco",1],["Privanzas Niza",1],["Privanzas Pamplona",1],["Real de San Agustin",0],["Real Del Valle",0],["Rincón de las Garzas",0],["Rincón del Campestre",0],["Santa Fe",0],["Valle de San Agustin",0],["Villas Carmel",0],["Zona San Agustín Campestre",0],["Zona Valle Oriente Sur",0]]],"66279":["19","019","San Pedro Garza García",0,[["Punto Central",1]]],"66280":["19","019","San Pedro Garza García",0,[["Balcones Del Valle",0],["Bosques de La Sierra 1er Sector",0],["Bosques de La Sierra 2do Sector",0],["Bosques de La Sierra 3er Sector",0],["Colinas de La Sierra Madre",0],["Pedregal Del Valle",0],["Villa Del Pedregal",0],["Villas Crisantemo",0],["Villas Del Pedregal",0],["Zona Bosques de la Sierra",0]]],"66285":["19","019","San Pedro Garza García",0,[["Sierra Nevada",0],["Villas del Valle",0],["Zona Bosques del Valle",0],["Zona Colinas Sierra Madre",0],["Zona Valle San Ángel",0]]],"66286":["19","019","San Pedro Garza García",0,[["Colonial La Sierra",0],["El Santuario",1],["Residencial Sierra Del Valle",0],["Zona el Santuario",0]]],"66287":["19","019","San Pedro Garza García",0,[["Lomas Del Rosario",0],["Zona Pedregal del Valle",0]]],"66290":["19","019","San Pedro Garza García",0,[["Bosques de San Ángel Sector Palmillas",0],["Loma Blanca",0],["Olinalá",0],["Valle de San Ángel Rincón Francés",0],["Valle de San Ángel Sect Español",0],["Valle de San Angel Sect Frances",0],["Valle de San Ángel Sect Jardines",0],["Valle de San Ángel Sect Mexicano",0]]],"66295":["19","019","San Pedro Garza García",0,[["Comercial Alpino Chipinque",0],["Hacienda de Carrizalejo",0],["Joya del Venado",0],["Lomas de San Angel",0],["Zona Alpino",0]]],"66296":["19","019","San Pedro Garza García",0,[["Colinas de San Angel 1er Sector",0],["Colinas de San Ángel 2do Sector",0]]],"66297":["19","019","San Pedro Garza García",0,[["La Joya de La Corona",1],["Las Alondras",0],["Los Encinos",0],["Residencial Chipinque 1 Sector",0],["Residencial Chipinque 2 Sector",1],["Residencial Chipinque 3 Sector",1],["Residencial Chipinque 4 Sector",1],["Villa Chipinque",0],["Villas La Rivera",0],["Zona Loma Blanca",0],["Zona Residencia Chipinque",22]]],"66350":["19","048","Ciudad Santa Catarina",0,[["Cerrada del Valle",1],["Cerrada del Valle Plus",1],["El Castillo",22],["Lázaro Cárdenas",0],["Mirador de Santa Catarina",0],["Nueva Santa Catarina",0],["Real del Valle 1 Sector",0],["Real del Valle 2 Sector",24],["Res. Panorámica",0],["Santa Catarina Centro",0],["Santa Martha I",0],["Santa Martha II",0]]],"66353":["19","048","Ciudad Santa Catarina",0,[["El Paraíso",0],["Priv San Patricio",0],["Residencial la Huasteca",22]]],"66354":["19","048","Ciudad Santa Catarina",0,[["Bosques de La Huasteca",0],["Enrique Rangel",0],["Inf la Huasteca",0],["Inf Santa Catarina",3],["Infonavit La Huasteca Quinta Sección",0],["Infonavit La Huasteca Séptima Sección",0],["Infonavit La Huasteca Sexta Sección",0],["La Huasteca 1er Sect",3],["La Huasteca 2o Sect",3],["La Huasteca 3",0],["La Huasteca Infonavit 4o Sect",3],["Loma Pelona",0],["Los Vitrales",0],["Mirador de la Huasteca",0],["Misión de la Huasteca",1],["Pedregal de La Huasteca",0],["Priv Sierra Madre",0],["Privadas la Huasteca",0],["Ventanas de La Huasteca",0]]],"66355":["19","048","Ciudad Santa Catarina",1,[["Parque Industrial Atlas",18]]],"66356":["19","048","Ciudad Santa Catarina",0,[["Alfonso Martinez Dominguez",0],["Praderas Del Castillo",0],["Privada 10 de Mayo",0]]],"66357":["19","048","Ciudad Santa Catarina",0,[["Balcones de Santa Catarina (fomerrey 134)",0],["Fomerrey 134",3],["Hacienda de Santa Catarina",0],["Paseo de La Sierra",0]]],"66358":["19","048","Ciudad Santa Catarina",0,[["Cordilleras Del Virrey",0],["Cumbres de Santa Catarina",0],["Cumbres de Santa Catarina 1 Sec",0],["Cumbres de Santa Catarina 2 Sec",0],["Cumbres de Santa Catarina 3 Sec",0],["Gral Naranjo",0],["Las Catarinas",0],["Luis Echeverría Alvarez",0],["Paseo de Santa Catarina",0],["Pedregal de Santa Catarina",1],["Portal de Santa Catarina",0],["Puerta Del Sol",0],["Residencial de La Sierra",22],["Zimex",0],["Zimix Amp",24],["Zimix Norte",0],["Zimix Sección Leones",0],["Zimix Sur",0]]],"66359":["19","048","Ciudad Santa Catarina",0,[["Bosques de Santa Catarina",1],["Inf Lomas de Santa Catarina",0],["La Puerta de La Huasteca",1],["Las Anacuas",0],["Lomas Altas",1],["Lomas de Santa Catarina",0],["Mirador de las Mitras",0],["Prados de Santa Catarina",0],["Privadas de La Montaña",1],["Residencial Santa Cecilia I",1],["Residencial Santa Cecilia II",1],["Robles de Santa Catarina",0],["Torres de Santa Catarina",0],["Universidad Tecnológica de Santa Catarina",8]]],"66360":["19","048","Ciudad Santa Catarina",0,[["Adolfo Lopez Mateos",3],["Colinas de Santa Catarina",0],["El Obispo JOMYCO",18],["Hacienda San Jose",0],["Ind Unidad Nacional",0],["Industrial Fico",0],["Industrial Monte de los Olivos",1],["Inf Cuauhtémoc Infonavit",3],["Inf. Adolfo López Mateos",3],["La Joya",1],["Misión Santa Catarina",1],["Residencial Cuauhtémoc",0]]],"66362":["19","048","Ciudad Santa Catarina",0,[["Bosques del Poniente",1],["El Molino",0],["Ex Hacienda los Arredondos",0],["Indalecio Vázquez",0],["Jardines de Santa Catarina",0],["Jardines de Santa Catarina 1",0],["Jardines de Santa Catarina 2",0],["Las Margaritas",1],["Mercado de Abastos Poniente",0],["Paseo del Parque",1],["Paseo del Prado",1],["Pio XII",0],["Privada 5 de Mayo",0],["Residencial Arvore",1],["Rincón de las Huertas",0],["Valle de Santa Cruz",1],["Villas del Poniente Las Granadas",1]]],"66363":["19","048","Ciudad Santa Catarina",0,[["El Escorial",0],["Labores Nuevas",0],["Senderos",0]]],"66364":["19","048","Ciudad Santa Catarina",0,[["Praderas de Santa Catarina",0],["Unión del Noreste",0]]],"66365":["19","048","Ciudad Santa Catarina",0,[["Mártires de Cananea",0],["Prados Del Rey",0],["Prados Del Sol",0],["Rincón de La Huasteca",0],["Villas Del Mirador",1]]],"66366":["19","048","Ciudad Santa Catarina",0,[["Provivienda Tepeyac",0],["Tepeyac",0]]],"66367":["19","048","Ciudad Santa Catarina",0,[["Bosques la Huasteca",1],["Del Poniente",9],["El Frutal",0],["El Obispo",18],["Hacienda el Palmar",1],["Huasteca del Valle I",0],["Industrial las Anacuas",0],["Industrial Marfer",9],["Industrial Martel de Santa Catarina",9],["Industrial Santa Catarina",18],["La Puerta",9],["Los Viñedos",1],["Norberto Aguirre",0],["Parque Ind del Pte Kalos",9],["Parque Industrial La Esperanza",9],["Parque Industrial los Nogales",0],["Parque Industrial Milenium",18],["Parque Industrial Pedreras",18],["Privadas de Santa Catarina",0],["Privadas de Santa Catarina Sector Elite",1],["Puerta de las Mitras",0],["Residencial de Santa Catarina",0],["T.A.D. Pemex Refineria",18],["Unidad Nacional II",0]]],"66368":["19","048","Ciudad Santa Catarina",0,[["Industrial las Palmas",9],["Micro Empresarios",0],["Parque 300",18],["Real de Santa Catarina",1],["Rincón de La Villa",0],["Rincón de las Palmas",0],["Rincón Del Poniente",0],["San Francisco",0]]],"66369":["19","048","Ciudad Santa Catarina",0,[["La Conquista",0],["Las Almenas",0],["Las Sombrillas",0],["Lomas del Pte",0],["Misión de las Villas",0],["San Gilberto",0],["Visión de la Huasteca",1]]],"66370":["19","048","Ciudad Santa Catarina",0,[["Industrias del Poniente",18]]],"66373":["19","048","Ciudad Santa Catarina",0,[["27 de Mayo",0]]],"66374":["19","048","Ciudad Santa Catarina",0,[["Virginia Tafich",0]]],"66375":["19","048","Ciudad Santa Catarina",0,[["29 de Julio",0],["Vista a la Sierra",1]]],"66376":["19","048","Ciudad Santa Catarina",0,[["El Lechugal",0],["Santa Catalina",0],["Santa Julia",0]]],"66377":["19","048","Ciudad Santa Catarina",0,[["Las Sierras",0],["San Gregorio",0]]],"66378":["19","048","Ciudad Santa Catarina",0,[["Aurora",0],["Aurorita",0]]],"66390":["19","048","NULL",1,[["Desarrollo Industrial Monterrey",1],["Parque Industrial Milimex",0]]],"66400":["19","046","San Nicolás de los Garza",0,[["San Nicolás de los Garza Centro",0]]],"66409":["19","046","San Nicolás de los Garza",0,[["Secretaria de Hacienda y Crédito Publico 141",10]]],"66410":["19","046","San Nicolás de los Garza",0,[["Benito Juárez",0],["Constituyentes Del 17",0],["Ignacio Ramirez",0],["La Enramada",0],["Las Alamedas",0],["México Lindo",0],["Miraflores Sector 1",0],["Miraflores Sector 2",0],["Miraflores Sector 3",0],["Nicolás Bravo",0],["Nicolás Bravo Sect 2",0],["Privada Sendero Anáhuac",0]]],"66412":["19","046","San Nicolás de los Garza",0,[["Centro de Desarrollo Comunitario CEDECO",10]]],"66413":["19","046","San Nicolás de los Garza",0,[["Bosques Del Roble",0],["Bosques del Roble Sector 2",0],["El Naranjal",0],["Huertas de San Bartolo",0],["Rincón del Roble",0],["San Bartolo",0],["San Isidro",0]]],"66414":["19","046","San Nicolás de los Garza",0,[["El Fundador",0],["Jardines de San Nicolás",0],["Residencial El Roble",0],["Residencial San Nicolás",0],["Roble San Nicolás",0],["Roble San Nicolás Sector 2",0],["Roble San Nicolás Sector 3",0],["Roble San Nicolás Sector 4",0]]],"66415":["19","046","San Nicolás de los Garza",0,[["Fomerrey 4 Mujeres Ilustres",1],["Héroes de México",0],["Héroes de México Sector 2",0],["Héroes de México Sector 3",0],["Villa Luz",0]]],"66417":["19","046","San Nicolás de los Garza",0,[["Anáhuac Sendero",1],["Hacienda del Roble Sector 2",1],["Hacienda El Roble",1],["La Nogalera",0],["La Nogalera Sector 2",0],["La Nogalera Sector 3",0],["Portal del Roble",1],["Residencial los Nogales",1],["Valle de Las Alamedas",0],["Valle Del Roble",0],["Villas Del Roble",0]]],"66418":["19","046","San Nicolás de los Garza",0,[["Centenario II",0],["Residencial Roble Sector 2",0],["Valle Dorado",0],["Valle Sol",1],["Viejo Roble",0],["Viejo Roble Sector 2",0],["Viejo Roble Sector 3",0]]],"66420":["19","046","San Nicolás de los Garza",0,[["Cerradas Del Roble",1],["Iturbide",0],["Iturbide Sector 2",0],["Iturbide Sector 3",0],["Las Villas",0],["Residencial Periférico",0],["Residencial Periférico Sector 2",0],["Residencial Periférico Sector 3",0],["Villa Universidad",0],["Villazul",0]]],"66422":["19","046","San Nicolás de los Garza",0,[["Balcones de Anáhuac",0],["El Mirador de San Nicolás (fomerrey 129)",0],["Hacienda de Anáhuac",0],["Paraíso de Anáhuac",1],["Reserva de Anahuac",1],["Residencial Anáhuac Zona Norte",0],["Rincón de Anáhuac",0],["Villas Anáhuac Sector 2",0],["Villas de Anáhuac",0]]],"66423":["19","046","San Nicolás de los Garza",0,[["Nuevo Periférico Sector 1",0],["Nuevo Periférico Sector 2",0],["Nuevo Periférico Sector 3",0]]],"66424":["19","046","San Nicolás de los Garza",0,[["Periférico Norte",0]]],"66425":["19","046","San Nicolás de los Garza",0,[["Barragán",9],["Colinas de Anahuac",1],["Estación Ramon Treviño",0],["Getsemani",0],["Privada Residencia Hacienda Anáhuac",1],["Stiva",9],["Tabachines",0]]],"66427":["19","046","San Nicolás de los Garza",0,[["Villa Real Sector 2",0],["Villarreal",0]]],"66428":["19","046","San Nicolás de los Garza",0,[["Casa Bella Sector 1",0],["Casa Bella Sector 2 1a Etapa",0],["Casa Bella Sector 2 2a Etapa",0],["Casa Bella Sector 3",0],["Las Misiones",0],["Privada Casa Bella",0]]],"66430":["19","046","San Nicolás de los Garza",0,[["Betel",0],["Congregación Mariano Escobedo",0],["El Refugio Sector 1",0],["El Refugio Sector 2",0],["Francisco Villa",0],["La Gloria",0],["Los Álamos",0],["Los Nogales",0],["Miraflores Sector 4",0],["Portal Del Roble",0],["Rincón de los Álamos",1],["San Antonio",0],["San Ignacio",1],["Santa Maria",0]]],"66434":["19","046","San Nicolás de los Garza",0,[["Rivera San Nicolás",0]]],"66435":["19","046","San Nicolás de los Garza",0,[["Rincón de los Cedros",0]]],"66436":["19","046","San Nicolás de los Garza",0,[["Las Nuevas Puente",0],["Praderas de Santo Domingo",0]]],"66437":["19","046","San Nicolás de los Garza",0,[["Los Nogales",3],["Poblado de Santo Domingo",0],["Valle de San Carlos",0],["Vicente Guerrero (fomerrey 46)",0],["Villas Santo Domingo",0]]],"66438":["19","046","San Nicolás de los Garza",0,[["Valle de las Flores",0],["Valle de Las Flores Sector 2",0],["Valle de Santo Domingo 1er Sector",0],["Valle de Santo Domingo Sector 3",0],["Villas de Santo Domingo Sector 2",0]]],"66440":["19","046","San Nicolás de los Garza",0,[["Ciudad Mezquital",0],["Los Morales",0],["Los Morales Sector 2",0],["Los Nogales (Fomerrey 44)",0],["Nuevo Mezquital",0],["Torres de Santo Domingo",0],["Unidad Laboral 1er. Sector",3],["Unidad Laboral Sector 2",3]]],"66443":["19","046","San Nicolás de los Garza",0,[["Sin Nombre",0]]],"66444":["19","046","San Nicolás de los Garza",0,[["Carmen Romano de Lopez Portillo (fomerrey 27)",0],["Estación Lagrange",0],["Fuentes de Anáhuac",1],["Paseo de los Andes Sector 1",0],["Paseo de Los Andes Sector 2 Sección A y B",0],["Paseo de Los Andes Sector 3",0],["Pedregal de Santo Domingo",0],["Pedregal de Santo Domingo Sector 2",0],["Pedregal de Santo Domingo Sector 3",0],["Prados de Santo Domingo Sector 1",0],["Privada Santo Domingo",2]]],"66445":["19","046","San Nicolás de los Garza",0,[["Jardines Del Mezquital",0],["Los Parques",0],["Valle del Mezquital (Fomerrey 30)",0]]],"66446":["19","046","San Nicolás de los Garza",0,[["Anáhuac la Escondida",1],["Balcones de Santo Domingo",0],["Paseo  San Nicolás",1],["Paseo San Nicolás",0],["Real Anáhuac",1]]],"66447":["19","046","San Nicolás de los Garza",0,[["Santo Domingo (Fom. 34)",0]]],"66448":["19","046","San Nicolás de los Garza",0,[["Arboledas de Santo Domingo",0],["Industrial los Parques",1],["Los Naranjos Sect 4",0],["Los Naranjos Sector 1",0],["Los Naranjos Sector 2",0],["Los Naranjos Sector 3",0],["Residencial Santo Domingo",0]]],"66449":["19","046","San Nicolás de los Garza",0,[["Aquiles Serdán (fom. 33)",0],["Arboledas Del Mezquital",0],["Colonial",0],["Fomerrey 118",0],["Fomerrey 119",0],["Hacienda de Santo Domingo",0],["Parques de Santo Domingo",0],["Residencial Santo Domingo Sector 2",0],["Unidad Habitacional Torres de Santo Domingo",3]]],"66450":["19","046","San Nicolás de los Garza",0,[["Anáhuac",0],["Avita Anahuac",1],["Chapultepec",0],["Cuauhtémoc",0],["Cuauhtémoc Sector 2",0],["Cuauhtémoc Sector 3",0],["El Roble",0],["El Roble Sector 2",0],["Lomas del Roble Sector 1",0],["Lomas del Roble Sector 2",0],["Pedregal de Anáhuac 1 Sector",1],["Pedregal de Anáhuac 2 Sector",1],["Prival de Anahuac",1],["Valle de Anáhuac",0],["Viejo Anáhuac",0]]],"66452":["19","046","San Nicolás de los Garza",0,[["Hojalata y Lamina Sa",10]]],"66455":["19","046","San Nicolás de los Garza",0,[["Ciudad Universitaria",0]]],"66456":["19","046","San Nicolás de los Garza",0,[["Ancestra",1],["Parque Anáhuac",0],["Potrero Anáhuac",0],["Potrero de Anáhuac Sector 2",0],["Potrero de Anáhuac Sector 3",0],["Villa las Puentes",0]]],"66457":["19","046","San Nicolás de los Garza",0,[["Residencial Anáhuac",0]]],"66458":["19","046","San Nicolás de los Garza",0,[["Roble Norte",0]]],"66459":["19","046","San Nicolás de los Garza",0,[["La Joroba",0],["Nuevo Laredo",0],["Royal",22]]],"66460":["19","046","San Nicolás de los Garza",0,[["Año de Juárez (fomerrey 86)",0],["Jardín de las Puentes",0],["Las Puentes Sector 1",0],["Las Puentes Sector 10",1],["Las Puentes Sector 11",1],["Las Puentes Sector 12",1],["Las Puentes Sector 14",1],["Las Puentes Sector 15",1],["Las Puentes Sector 2",1],["Las Puentes Sector 3",1],["Las Puentes Sector 4",1],["Las Puentes Sector 5",1],["Las Puentes Sector 6",1],["Las Puentes Sector 7",1],["Las Puentes Sector 8",1],["Las Puentes Sector 9",1],["Paseo de las Puentes",0],["Residencial las Puentes Sector 1 Sección A",0],["Rincón de las Puentes",0],["Rincón de los Andes",0],["Valle de las Puentes",0],["Villa las Puentes",0]]],"66463":["19","046","San Nicolás de los Garza",0,[["Bosques de Anáhuac",1],["Jardines de Anáhuac Sector 1",0],["Jardines de Anáhuac Sector 2",0],["Jardines de Anáhuac Sector 3",1]]],"66464":["19","046","San Nicolás de los Garza",0,[["Residencial Nova",0],["Residencial Nova Sector 2",0],["Residencial Nova Sector 3",0]]],"66465":["19","046","San Nicolás de los Garza",0,[["Arboledas de San Jorge",0],["Colonial las Puentes",1],["Hacienda las Puentes",20],["Quinta las Puentes",0],["Residencial Las Palmas Sector 1",0],["Residencial Las Palmas Sector 2",0],["Residencial Las Palmas Sector 3",0],["Riveras de las Puentes",0],["Riveras de Las Puentes Sector 2",0]]],"66466":["19","046","San Nicolás de los Garza",0,[["Balcones de las Puentes",0]]],"66467":["19","046","San Nicolás de los Garza",0,[["Residencial Las Puentes Sector 1 Sección B",0],["Residencial Las Puentes Sector 1 Sección C",0],["Residencial Las Puentes Sector 2 Sección A",0],["Residencial Las Puentes Sector 2 Sección B",0],["Residencial Las Puentes Sector 3 Sección B",0],["Residencial Las Puentes Sector 4 Sección B",0],["Residencial Las Puentes Sector 5 Sección B",0]]],"66468":["19","046","San Nicolás de los Garza",0,[["Jardines de Santo Domingo",0]]],"66469":["19","046","San Nicolás de los Garza",0,[["Julio Camelo Treviño",0],["Las Esperanzas",0],["Villa Esperanza",0]]],"66470":["19","046","San Nicolás de los Garza",0,[["Alcatraces Residencial",1],["Andalucía",0],["Costa del Sol 1er Sector",0],["Costa del Sol Sector 2",0],["Del Lago Sect 2",0],["Del Vidrio Oriente Sect 3",24],["Del Vidrio Oriente Sect 4",24],["Del Vidrio Oriente Sect 5",24],["Industrias Del Vidrio Oriente",24],["Los Laureles",0],["Miguel Aleman",0],["Paseo de los Angeles",0],["Residencial los Morales",1],["Residencial Paseo de los Angeles",0],["Rincón Del Oriente",0],["San Benito Del Lago",1],["Tacuba",0],["Villa Luis",22],["Villas de Oriente Sector 1",0],["Villas de Oriente Sector 2",0],["Villas de Oriente Sector 3",0]]],"66473":["19","046","San Nicolás de los Garza",0,[["Blas Chumacero 2 Sector",23],["Blas Chumacero CTM",23],["Bosques de Lindavista",0],["Bosques de Lindavista 2 Sector",0],["Bosques de Lindavista Sector Diamante",1],["La Talaverna",0],["La Talaverna CROC",3],["Los Cipreses",0],["Los Olivos",22],["Parque La Talaverna",0],["Villas de San Miguel",0]]],"66474":["19","046","San Nicolás de los Garza",0,[["Cipreses Residencial 2 Sector",0],["Cipreses Residencial 3 Sector",0],["Cipreses Residencial 4 Sector",0],["Cipreses Residencial 5 Sector",0]]],"66475":["19","046","San Nicolás de los Garza",0,[["Casa Blanca",0],["Jardines de Casa Blanca",0],["Jardines de Casa Blanca Sector 2",0],["Los Ángeles Sector 7",1],["Los Ángeles Sector 8",1],["San Ángel Casa Blanca",0],["Villas de Casa Blanca",0],["Villas de Casa Blanca Sector 2",0],["Villas de Casa Blanca Sector 3",0]]],"66476":["19","046","San Nicolás de los Garza",0,[["Ciudad Minera",0],["Ideal Minera",0],["La Estancia Sector 1",0],["La Estancia Sector 2",0],["La Estancia Sector 3",0],["La Estancia Sector 4",0],["Los Reales Sector 1",0],["Los Reales Sector 2",0]]],"66477":["19","046","San Nicolás de los Garza",0,[["Del Lago Sector 1",0],["Hacienda las Fuentes",1],["Hacienda los Angeles",0],["La Fe",0],["Residencial Santa Fé",1]]],"66478":["19","046","San Nicolás de los Garza",0,[["Arboledas de San Cristóbal",0],["Cerradas de Casa Blanca",1],["Fresnos del Lago",0],["Los Ángeles Sector 3",3],["Los Ángeles Sector 4",3],["Los Ángeles Sector 5",3],["Los Pinos",1],["Misión de Casa Blanca",0],["Misión de Casa Blanca 2do Sector",0],["Misión de San Cristóbal",0],["Palmas Diamante",1],["Privadas de Casa Blanca",0],["Quinta Montecarlo",1],["Residencial los Angeles Sect 1",0],["Residencial los Angeles Sect 2",0],["Residencial San Cristóbal Sector 1",22],["Residencial San Cristóbal Sector 2",0],["Residencial San Cristóbal Sector 3",0],["Rincón de Casa Blanca 1er Sector",0],["Rincón de Casa Blanca Sector 2",0],["Rincón de los Ángeles",1],["Valle Casa Blanca",0],["Villas de San Cristóbal Sector 2",0],["Villas San Cristóbal 1er Sector",0]]],"66479":["19","046","San Nicolás de los Garza",0,[["Margarita Salazar",0]]],"66480":["19","046","San Nicolás de los Garza",0,[["Azteca Fomerrey 11",0],["Bosques Del Nogalar",0],["Bosques del Nogalar 2 Sector",0],["Deportivo Lagrange",0],["Diaz Ordaz",0],["Futuro Nogalar Sector 2",0],["Garza Cantu",0],["INFONAVIT Conductores",0],["Jose Lopez Portillo",0],["Nogalar",0],["Prados Del Nogalar (fomerrey 11)",0],["Residencial Nogalar",0],["Valle Azteca (fomerrey 12)",0],["Valle de las Granjas (fomerrey 13)",0],["Valle Del Nogalar",0]]],"66482":["19","046","San Nicolás de los Garza",0,[["Mercado de Abastos Estrella",0],["Predio Aldape",0]]],"66484":["19","046","San Nicolás de los Garza",0,[["Antiguo Nogalar",0],["Futuro Nogalar Sector 1",0],["Industrial Nogalar",0]]],"66485":["19","046","San Nicolás de los Garza",0,[["Bosques de Santo Domingo (fomerrey 92)",0],["Rincón Del Nogalar",0]]],"66486":["19","046","San Nicolás de los Garza",0,[["4 de Octubre Fomerrey 72",0],["Hacienda Nogalar",0],["Jardines Del Nogalar (fomerrey 28)",0],["La Morena (fomerrey 65)",0],["Nogalar Infonavit",3],["Privada Nogalar",1],["Salvador Allende",0]]],"66488":["19","046","San Nicolás de los Garza",0,[["27 de Julio",0],["El Agarron",0],["Floridos Bosques Del Nogalar (fomerrey 90)",0],["Luis M Farias",0]]],"66489":["19","046","San Nicolás de los Garza",0,[["Lagos de Chapultepec (fomerrey 69)",0]]],"66490":["19","046","San Nicolás de los Garza",0,[["Antiguo Corral de Piedra 1er Sector",0],["Antiguo Corral de Piedra 2 Sector",0],["Ciudad Ideal",0],["Ciudad Ideal Sector 3",0],["Ciudad Ideal Sector 4",0],["Colonial Lagrange",0],["Constituyentes de Queretaro Sector 1",0],["Constituyentes de Queretaro Sector 2",3],["Constituyentes de Queretaro Sector 3",3],["Constituyentes de Queretaro Sector 4",3],["Constituyentes de Queretaro Sector 5",3],["Constituyentes de Queretaro Sector 6",3],["Del Vidrio",0],["Francisco Garza Sada",0],["Industrias del Vidrio Amp. Oriente Sector 2",0],["Industrias del Vidrio Ampliación Norte Sector 1",0],["Industrias del Vidrio Ampliación Norte Sector 2",0],["Industrias del Vidrio Ampliación Norte Sector 3",0],["Industrias del Vidrio Ampliación Norte Sector 4",0],["Industrias del Vidrio Sector 1",0],["INFONAVIT Valle de Lagrange",0],["Nuevo Mundo",0],["Peña Guerra",0],["Residencial Rivera Sector 2",0],["Residencial Riviera Sector 1",1]]],"66492":["19","046","San Nicolás de los Garza",0,[["Del Vidrio",24],["Industrias Del Vidrio",24]]],"66493":["19","046","San Nicolás de los Garza",0,[["Conductores Monterrey Sa",10]]],"66494":["19","046","San Nicolás de los Garza",0,[["Central de Carga",0]]],"66495":["19","046","San Nicolás de los Garza",0,[["Hacienda los Morales Sector 1",0]]],"66496":["19","046","San Nicolás de los Garza",0,[["Alejandría",1],["Fidel Velázquez Sánchez Sector 1",0],["Fidel Velázquez Sect 2",0],["Hacienda los Morales Sector 2",0],["Hacienda los Morales Sector 3",0],["Hacienda los Morales Sector 4",0],["Industrias del Vidrio Amp. Oriente Sector 3",0],["Industrias del Vidrio Ampliación Oriente Sector 5",0],["Industrias del Vidrio Sector 4",0],["Valle de los Morales",0],["Vivenza",1]]],"66499":["19","046","San Nicolás de los Garza",0,[["Hacienda Lagrange",0],["Los Mezquites",22],["Residencial San Felipe",0]]],"66550":["19","010","NULL",1,[["El Carmen Centro",0],["El Mirador",0],["Villas de los Arcos 1er Sector",1]]],"66553":["19","010","NULL",1,[["Alianza Real",0],["Rincón del Carmen",0]]],"66556":["19","010","NULL",1,[["Parque Industrial el Carmen",18]]],"66557":["19","010","NULL",1,[["Paseo del Carmen",0],["Privadas del Carmen",0]]],"66559":["19","010","NULL",1,[["El Jaral",20]]],"66563":["19","010","NULL",1,[["Los González",0]]],"66580":["19","010","NULL",1,[["El Jaral",1],["Privadas El Jaral",1],["Villas del Jaral",1]]],"66583":["19","010","NULL",1,[["Buena Vista",7]]],"66600":["19","006","Ciudad Apodaca",0,[["Apodaca Centro",0],["Futuro Apodaca",0],["Homero Sepúlveda",0],["Manuel Villarreal",0],["Moderno Apodaca I",0],["Moderno Apodaca II",0],["Parque Industrial Kuadrum",9],["Presidentes Municipales",0],["San Francisco",0],["Santa Rosa II",0]]],"66603":["19","006","Ciudad Apodaca",0,[["Parque Industrial Elicán",18],["Parque Industrial Kalos",18],["Parque Industrial Kronos",18],["Parque Industrial Monterrey",18],["Radica",0],["Residencial San Francisco",0]]],"66604":["19","006","Ciudad Apodaca",0,[["Altabrisa",1],["Bosque de Agua",1],["Burócratas Municipales",0],["Casas Reales",0],["Crystal Lagoons",1],["Los Castaños Privada Rsidencial",1],["Los Molinos San Francisco",1],["Misión de los Olivos",1],["San Francisco Sector Norte",1],["Santa Rosa",1]]],"66605":["19","006","Ciudad Apodaca",0,[["Benito Juárez",0],["Interamerican",1],["Nova Apodaca",0],["Pedregal de Apodaca",0],["Residencial Apodaca",1],["Teresita",0]]],"66606":["19","006","Ciudad Apodaca",0,[["Rinconada Colonial",1]]],"66607":["19","006","Ciudad Apodaca",0,[["Hacienda los Guajardo",1],["Paraje Santa Rosa",0],["Paraje Santa Rosa Sector Norte",0],["Paseo de los Nogales Santa Rosa",1],["Quinta Real",1],["Santa Rosa de Lima",0],["Valle de Salduero",1],["Valle la Rioja",1]]],"66609":["19","006","Ciudad Apodaca",0,[["Privalia Concordia",1]]],"66610":["19","006","Ciudad Apodaca",0,[["Antigua Santa Rosa",1],["Balcones de Santa Rosa 1",0],["Bonaterra",1],["Bosques de Santa Rosa",1],["Ébanos IX",0],["Ébanos VII",0],["Ébanos VIII",0],["Ébanos X",0],["Ébanos XI",0],["Ébanos XII",0],["Ex Hacienda Santa Rosa",0],["Las Palmas",22],["Los Soles",1],["Pedregal del Valle",1],["Prados de Santa Rosa",0],["Privadas de Santa Rosa",1],["Quinta Colonial Apodaca",1],["Rincón de Santa Rosa",0],["Sierra la Esperanza",1],["Valle de los Nogales",1],["Valle de los Nogales Residencial",1],["Ventura de Santa Rosa",0],["Villas de Santa Rosa",1]]],"66612":["19","006","Ciudad Apodaca",0,[["Andalucía",0],["Bosque Real I",0],["Bosque Real II",0],["Bosque Real III",0],["Cortijo las Palmas",0],["Cosmópolis",0],["Ébano Norte 3",0],["Ébano Norte IV",0],["Ébanos I",0],["Ébanos II",0],["Ébanos III",0],["Ébanos IV",0],["Ébanos Norte 1",0],["Ébanos Norte 2",0],["Ébanos V",0],["Ébanos VI",0],["El Molino",0],["Hacienda las Yucas",0],["Hacienda Santa Isabel",0],["Insurgentes",0],["Jardines de las Palmas",0],["Jardines de San Andres I",1],["Jardines de San Andres II",1],["Jardines de San Andres IV NT",1],["Jardines de San Andres V",1],["Jardines de San Andres VI",1],["Las Estancias",0],["Las Huertas",1],["Los Encinos",1],["Los Lirios",1],["Manantial I",0],["Manantial II",0],["Metroplex",0],["Misión de Fundadores",1],["Misión del Parque",1],["Misión San Jose",0],["Misión San José 2 Sector",0],["Nueva las Puentes III",0],["Nuevo las Puentes",0],["Prados de los Pinos",0],["Prados Del Virrey",0],["Privadas del Rey",0],["Real de San Andres",1],["San Agustín",0],["Santa Alicia",0],["Valle de Apodaca",0],["Valle de las Bugambilias",0],["Valle de las Palmas II",0],["Valle de las Palmas III",0],["Valle de las Palmas IV",0],["Valle de las Palmas V",1],["Valle de las Palmas VI",1],["Valle de San Andres I",0],["Valle San Andres II",0],["Valle San Andres III",0],["Valle San Andres IV",0],["Villa las Puentes",1],["Villas Premier",0]]],"66613":["19","006","Ciudad Apodaca",0,[["Balcones del Norte III",0],["El Vergel",6],["Fundadores",0],["Jardines de Monterrey I",0],["Jardines de Monterrey II",0],["Jardines de Monterrey III",0],["Los Amarantos",1],["Los Amarantos II",1],["Mirador del Topo",1],["Moisés Sáenz",0],["Parque Industrial Jardín de Monterrey I",0],["Paseo de Apodaca",1],["Residencial Moisés Sáenz",0],["Santa Elena",1]]],"66614":["19","006","Ciudad Apodaca",0,[["Arboledas de Santa Rosa",1],["Cosmópolis 8vo. Sector",1],["Los Altos",0],["Los Cenizos",1],["Milimex Santa Rosa",9],["Parque Industrial Azteca",9],["Paseo de Santa Rosa",1],["Portal de Santa Rosa",1],["Renaceres",1]]],"66616":["19","006","NULL",0,[["Cuartel General 7a. Z. M.",33],["Entronque Laredo-Salinas Victoria",0],["Parque Industrial Aeropuerto 1er Sector",9]]],"66620":["19","006","Ciudad Apodaca",1,[["Agua Fría",0],["Cerritos de Agua Fría",0],["Residencial Valle Azul",1],["Triana",1]]],"66623":["19","006","Ciudad Apodaca",0,[["Artemio Treviño",0],["Ciudad Natura",0]]],"66624":["19","006","Ciudad Apodaca",0,[["Pimsa Oriente",9]]],"66626":["19","006","Ciudad Apodaca",0,[["Almería",1],["Parque Industrial Milenium",9],["Parque Industrial Stiva",9],["Parque Industrial Villacero",9]]],"66627":["19","006","Ciudad Apodaca",0,[["ProLogis Park",9],["Technology Park",9]]],"66628":["19","006","Ciudad Apodaca",0,[["Parque de Investigación e Inovación Tecnológica",9]]],"66629":["19","006","Ciudad Apodaca",0,[["Monterrey (Gral. Mariano Escobedo)",19]]],"66630":["19","006","Ciudad Apodaca",0,[["Arboledas del Mezquital",1],["Cantizales",1],["Ejido Mezquital",0],["El Mezquital",0],["Francisco Elizondo",0],["Francisco Martinez",0],["Garcia Mireles",0],["Hacienda Del Moro",1],["Hacienda los Nogales",1],["Las Américas",0],["Privada 103",1],["Viejo Mezquital",0]]],"66632":["19","006","Ciudad Apodaca",0,[["Balcones Del Mezquital",0],["Cantu",0],["Cerradas de Santa Rosa 1S 1E",1],["Const. Casa Bella",0],["Desarrollo Industrial GP Apodaca 2",18],["Ex Hacienda San Francisco",1],["Hacienda Del Mezquital",0],["José María García Ponce",0],["Nuevo Mezquital",0],["Rincón de la Moraleja",1],["Valle Del Mezquital",0],["Villas del Mezquital",0]]],"66633":["19","006","Ciudad Apodaca",0,[["Álamos Del Parque",0],["Alianza",9],["Business Park Monterrey",9],["Deportivo Huinalá",1],["Deportivo Huinalá Mundialista",1],["Fresnos del Lago",0],["Hacienda Santa Fe",0],["Jardines de San Jorge",1],["Kalos la Encarnación",0],["La Encarnación",0],["Los Álamos",1],["Los Álamos III",0],["Los Arrecifes",0],["Mirador Huinalá",0],["Multipark Parque",18],["Noria Norte",0],["Noria Sur",0],["Parque Industrial Apodaca",0],["Parque Industrial J.M.",9],["Parque Industrial México",9],["Parque Industrial Omolap",9],["Privada Antigua Huinalá",1],["Privadas Del Parque",0],["Regio Parque Industrial",9],["Rincón de la Gloria",1],["Titán",9],["Torre de Campo",0],["Valle de los Álamos",0]]],"66634":["19","006","Ciudad Apodaca",0,[["Axis Mty",9],["Campestre CTM",0],["El Milagro",0],["Encinos Residencial",1],["Iltamarindo",1],["Independencia",3],["Jacarandas Sector 1",0],["Misión de San Patricio",1],["Privada la Castaña",0],["Privadas Premier",1],["Privadas Santa Fe",0],["Residencial las Provincias",1],["Valle de Huinalá",1],["Villas de Huinalá",1]]],"66635":["19","006","Ciudad Apodaca",0,[["Enramada I",0],["Enramada II",0],["Enramada III",0],["Enramada IV",0],["Enramada V",0],["Enramada VI",0],["Enramada VII",0],["Fresnos II",1],["Fresnos III",1],["Hacienda las Palmas",0],["Hacienda las Palmas II",0],["Hacienda los Encinos",0],["Hacienda los Pinos III",0],["Jardines de Apodaca",0],["Jardines de La Enramada",0],["Magnolias",1],["Mujeres Ilustres",0],["Nueva Democracia",0],["Paseo Palmas I",0],["Paseo Palmas II",0],["Paseo Palmas III",0],["Paseo Palmas IV",0],["Pinos III",0],["Pinos IV",0],["Pinos V",0],["Portal Anáhuac",1],["Praderas I",0],["Praderas II",0],["Valle de las Palmas I",0],["Villa Luz",0],["Villa Sol",0]]],"66636":["19","006","Ciudad Apodaca",0,[["Arboledas Del Virrey",0],["Cerrada Providencia",1],["Fresnos I",3],["Fresnos IV",1],["Fresnos IX",1],["Fresnos Norte",0],["Fresnos V",1],["Fresnos VI",1],["Fresnos VIII",1],["Fresnos X",1],["Hacienda los Pinos",0],["Hacienda los Pinos II",0],["Jardín de los Pinos II",0],["Jardines de los Pinos I",0],["La Hacienda",0],["La Hacienda II",0],["Los Robles",0],["Nuevo Amanecer 1",0],["Nuevo Amanecer 2",0],["Paseo de los Nogales",1],["Paseo de los Pinos II",0],["Pinos I",0],["Pinos II",0],["Prados de La Cieneguita",0],["Pradreras de La Enramada",0],["Residencial Palmas",1],["Santa Cecilia",1]]],"66637":["19","006","Ciudad Apodaca",0,[["Almacentro",18],["Industrial Martel",9],["Parque Industrial Milimex",0]]],"66640":["19","006","Ciudad Apodaca",0,[["Alberta Escamilla",0],["Balcones de Huinalá",0],["Colonial de Huinalá",0],["Hacienda San Gerardo",1],["Huinalá",0],["Jardines de Huinalá",0],["Lomas de Huinalá II",0],["Misión Real",1],["Parque Industrial San Andrés",9],["Prados Residencial",1],["Real de Apodaca",1],["Reforma",0],["San Andrés",1],["San Miguel Golondrinas",0]]],"66643":["19","006","Ciudad Apodaca",0,[["Hacienda el Campanario",1],["Los Olmos",1],["Misión San Pablo",1],["Paseo de las Flores",1],["Portal del Valle",1],["Santa Anita",1]]],"66644":["19","006","Ciudad Apodaca",0,[["Bugambilias Huinalá",1],["Parque Industrial San Carlos",9],["Real Hacienda de Huinalá",0],["Rincón de Huinalá",0],["Santa Mónica",0],["Treviño Elizondo",0],["Villas de San Carlos",0]]],"66645":["19","006","Ciudad Apodaca",0,[["Bosques de Huinalá",0],["Bosques de Huinalá 2 Sector",0],["Hacienda Del Carmen",0],["Jardines Del Virrey",0],["Padilla",0],["Parque Industrial el Sabinal",9],["Parque Industrial Huinalá",0],["Parque Industrial las Americas",9]]],"66646":["19","006","Ciudad Apodaca",0,[["Estancia Castaño",1],["Lomas de San Isidro",0],["Los Colibries",0],["Milenium Residencial",0],["Misión de Huinalá",1],["Mision de San Javier",0],["Portal de Huinalá",0],["Privada Dominio",1],["Privadas Canteras",1],["Privalia Huinalá",1],["Pueblo Nuevo",0],["Residencial San Benito",1],["Riveras de Huinalá",0],["San Isidro",1],["San Javier",0],["Tréboles",1]]],"66647":["19","006","Ciudad Apodaca",0,[["Acanto Residencial",0],["American Industries Apodaca",18],["Bosque del Sol",0],["Bosques de San Miguel",0],["Campestre Huinalá",0],["El Rosario",1],["Fuentes de Santa Lucia",0],["Hacienda las Margaritas",0],["Jardines de San Patricio",1],["Lomas de la Paz",1],["Lomas de San Miguel",0],["Los Candiles",0],["Los Olivos Residencial",22],["Los Pinceles",0],["Los Puertos",1],["Los Vitrales",0],["Mirasol Residencial",1],["Paseo de la Loma",1],["Paseo de las Fuentes",1],["Praderas de Huinalá",1],["Vivienda Digna",0]]],"66648":["19","006","Ciudad Apodaca",0,[["Cerrada la Toscana",1],["Colinas de San Miguel",0],["El Campanario",0],["Joyas Del Pedregal",0],["Lomas de Huinalá I",0],["Lomas Del Pedregal",0],["Los Tres Nogales",1],["Misión de Las Flores",0],["Misión de San Miguel",0],["Monte Alban II",0],["Parque Industrial la Silla",9],["Rincón de San Miguel",0],["Roberto Espinoza",0],["San Miguel",1],["Santa Fé",0],["Valle de San Miguel",1],["Valle Del Pedregal",0]]],"66649":["19","006","Ciudad Apodaca",0,[["Altaria Residencial",1],["Golondrinas",0],["Miguel Hidalgo",0],["Mixcoac",0],["Monte Albán",1],["Nueva Mixcoac",0],["Privada San Miguelito",1],["Quinta San Miguel",1],["Rincón de los Cristales",1],["San Ignacio",0],["San Miguel",0],["San Miguelito",1],["Sebastián Elizondo I",0],["Sebastián Elizondo II",0],["Ventura de Asís",1],["Ventura de Asís II",1],["Villas de Loreto",1]]],"66650":["19","041","NULL",0,[["Pesquería",13]]],"66653":["19","041","NULL",0,[["Villas Regina",1]]],"66655":["19","041","NULL",1,[["Arcos del Parque",1],["Colinas del Aeropuerto",0],["El Llano",1],["Las Haciendas",1],["Privadas del Roble",1],["Residencial Floresta",1],["Santa Engracia",0],["Zacatecas",12]]],"66657":["19","041","NULL",1,[["Airport Technology Park",18]]],"66660":["19","041","NULL",1,[["Las Aves Residencial and Golf Resort",1]]],"66670":["19","041","NULL",1,[["Dulces Nombres",13],["Las Águilas",0],["Las Escobas",0],["Misión Dulces Nombres",1],["Valle de Santa María",1]]],"66672":["19","041","NULL",0,[["Paseo San Javier",1]]],"66673":["19","041","NULL",0,[["Lomas de San Martín",1]]],"66674":["19","041","NULL",1,[["Jesús María",0]]],"66679":["19","041","NULL",1,[["La Arena",14]]],"66680":["19","041","NULL",1,[["Santa Maria La Floreña",20]]],"66683":["19","041","NULL",1,[["La Providencia",7]]],"66690":["19","041","NULL",1,[["Milpa",21]]],"66693":["19","041","NULL",1,[["Santa Maria Pesquería",14]]],"66700":["19","034","NULL",1,[["Marín",14],["Marín",13]]],"66708":["19","034","NULL",1,[["Guadalupe",20]]],"66750":["19","016","NULL",0,[["Doctor González",13]]],"66770":["19","016","NULL",1,[["Nuevo Repueblo",7]]],"66790":["19","016","NULL",1,[["La Venadera O San Antonio",7]]],"66793":["19","016","NULL",1,[["Los Peña",7]]],"66800":["19","042","NULL",0,[["Los Ramones",13]]],"66810":["19","042","NULL",1,[["Hidalgo",12]]],"66812":["19","042","NULL",1,[["El Peine",12]]],"66820":["19","042","NULL",1,[["Garza Gonzalez",12]]],"66824":["19","042","NULL",1,[["La Loma",21]]],"66825":["19","042","NULL",1,[["Repueblo de Oriente",12],["San Benito",12]]],"66826":["19","042","NULL",1,[["Los Angeles",7]]],"66827":["19","042","NULL",1,[["El Saucito",6]]],"66830":["19","042","NULL",1,[["San Isidro",20]]],"66835":["19","042","NULL",1,[["Ayancual",20]]],"66840":["19","042","NULL",1,[["El Carrizo",14]]],"66842":["19","042","NULL",1,[["El Carrizo",14]]],"66847":["19","042","NULL",1,[["Las Enramadas",7]]],"66848":["19","042","NULL",1,[["La Conquista",14]]],"66849":["19","042","NULL",1,[["El Porvenir",20]]],"66850":["19","027","NULL",0,[["Los Herreras",13]]],"66860":["19","027","NULL",1,[["San Vicente",12]]],"66861":["19","027","NULL",1,[["Guadalupe",20]]],"66865":["19","027","NULL",1,[["San Jose de La Laja",12]]],"66872":["19","027","NULL",1,[["San Agustin",12]]],"66880":["19","027","NULL",1,[["Barretosa",12]]],"66900":["19","003","NULL",0,[["Los Aldamas",13]]],"66910":["19","003","NULL",1,[["Los Aldamas",4]]],"66930":["19","003","NULL",1,[["Los Aldamas",21]]],"66940":["19","003","NULL",1,[["San Pedro",12]]],"66945":["19","003","NULL",1,[["La Palmita",12]]],"66950":["19","015","NULL",0,[["Doctor Coss",13]]],"66953":["19","015","NULL",1,[["Hacienda de Guadalupe",1],["Norte",4]]],"66955":["19","015","NULL",1,[["Francisco I Madero",12]]],"66960":["19","015","NULL",1,[["La Lajilla",12]]],"66963":["19","015","NULL",1,[["La Ceja",7]]],"66964":["19","015","NULL",1,[["Serafín",7]]],"66980":["19","015","NULL",1,[["Cantu",12]]]}